{
  "id": "6e82ed25-650e-49bc-91df-dfd0b92a8a41",
  "name": "Baliwag Lechon Manok",
  "slug": "baliwag-lechon-manok",
  "description": "A popular Filipino restaurant chain famous for their roasted chicken and liempo. Known for consistent quality, affordable prices, and signature lechon manok that's crispy on the outside and juicy inside.",
  "address": "Maginhawa St, Teacher's Village, Quezon City",
  "phone": "+63 2 8441 8888",
  "email": "",
  "website": "https://www.baliwag.com.ph",
  "coverImageUrl": "",
  "photosUrls": [],
  "operatingHours": {
    "monday": {
      "open": "09:00",
      "close": "21:00"
    },
    "tuesday": {
      "open": "09:00",
      "close": "21:00"
    },
    "wednesday": {
      "open": "09:00",
      "close": "21:00"
    },
    "thursday": {
      "open": "09:00",
      "close": "21:00"
    },
    "friday": {
      "open": "09:00",
      "close": "21:00"
    },
    "saturday": {
      "open": "09:00",
      "close": "21:00"
    },
    "sunday": {
      "open": "09:00",
      "close": "21:00"
    }
  },
  "priceRange": "$",
  "paymentMethods": [
    "cash",
    "credit-card",
    "gcash"
  ],
  "tags": [
    "filipino",
    "roasted-chicken",
    "budget-friendly",
    "family-friendly",
    "chain"
  ],
  "amenities": [
    "dine-in",
    "takeout",
    "delivery"
  ],
  "cuisineTypes": [
    "filipino"
  ],
  "specialties": [
    "lechon-manok",
    "liempo",
    "roasted-chicken",
    "filipino-food"
  ],
  "latitude": 14.6431,
  "longitude": 121.0648,
  "createdAt": "2025-11-09T00:00:00Z",
  "updatedAt": "2025-11-09T00:00:00Z",
  "createdBy": "Joff Tiquez"
}
